wfcommons/__init__.py
wfcommons/utils.py
wfcommons/version.py
wfcommons/common/__init__.py
wfcommons/common/file.py
wfcommons/common/machine.py
wfcommons/common/task.py
wfcommons/common/workflow.py
wfcommons/wfbench/__init__.py
wfcommons/wfbench/bench.py
wfcommons/wfbench/translator/__init__.py
wfcommons/wfbench/translator/abstract_translator.py
wfcommons/wfbench/translator/airflow.py
wfcommons/wfbench/translator/bash.py
wfcommons/wfbench/translator/cwl.py
wfcommons/wfbench/translator/dask.py
wfcommons/wfbench/translator/nextflow.py
wfcommons/wfbench/translator/parsl.py
wfcommons/wfbench/translator/pegasus.py
wfcommons/wfbench/translator/pycompss.py
wfcommons/wfbench/translator/swift_t.py
wfcommons/wfbench/translator/taskvine.py
wfcommons/wfbench/translator/templates/dask_template.py
wfcommons/wfbench/translator/templates/flowcept_agent.py
wfcommons/wfbench/translator/templates/parsl_template.py
wfcommons/wfbench/translator/templates/pegasus_template.py
wfcommons/wfbench/translator/templates/pycompss_template.py
wfcommons/wfbench/translator/templates/taskvine_poncho.json
wfcommons/wfbench/translator/templates/taskvine_template.py
wfcommons/wfbench/translator/templates/cwl/folder.cwl
wfcommons/wfbench/translator/templates/cwl/shell.cwl
wfcommons/wfbench/translator/templates/cwl/wfbench.cwl
wfcommons/wfbench/translator/templates/nextflow/workflow.nf
wfcommons/wfbench/translator/templates/swift_t/workflow.swift
wfcommons/wfchef/__init__.py
wfcommons/wfchef/chef.py
wfcommons/wfchef/duplicate.py
wfcommons/wfchef/find_microstructures.py
wfcommons/wfchef/utils.py
wfcommons/wfchef/wfchef_abstract_recipe.py
wfcommons/wfchef/recipes/__init__.py
wfcommons/wfchef/recipes/blast/__init__.py
wfcommons/wfchef/recipes/blast/recipe.py
wfcommons/wfchef/recipes/blast/task_type_stats.json
wfcommons/wfchef/recipes/blast/__pycache__/__init__.cpython-311.pyc
wfcommons/wfchef/recipes/blast/__pycache__/__init__.cpython-312.pyc
wfcommons-1.2.dist-info/licenses/LICENSE
wfcommons-1.2.dist-info/METADATA
wfcommons-1.2.dist-info/WHEEL
wfcommons-1.2.dist-info/entry_points.txt
wfcommons-1.2.dist-info/top_level.txt
wfcommons-1.2.dist-info/RECORD
