Metadata-Version: 2.4
Name: wfcommons
Version: 1.2
Summary: A Framework for Enabling Scientific Workflow Research and Education
Author-email: WfCommons team <support@wfcommons.org>
License: GNU General Public License v3 (GPLv3)
Project-URL: Homepage, https://wfcommons.org
Project-URL: Source, https://github.com/wfcommons/wfcommons
Project-URL: Documentation, https://docs.wfcommons.org
Project-URL: Tracker, https://github.com/wfcommons/WfCommons/issues
Classifier: License :: OSI Approved :: GNU General Public License v3 (GPLv3)
Classifier: Operating System :: OS Independent
Classifier: Programming Language :: Python :: 3
Classifier: Programming Language :: Python :: 3.9
Classifier: Programming Language :: Python :: 3.10
Classifier: Programming Language :: Python :: 3.11
Classifier: Programming Language :: Python :: 3.12
Classifier: Programming Language :: Python :: 3.13
Classifier: Intended Audience :: Developers
Classifier: Intended Audience :: Education
Classifier: Intended Audience :: Science/Research
Classifier: Natural Language :: English
Classifier: Topic :: Documentation :: Sphinx
Classifier: Topic :: System :: Distributed Computing
Requires-Python: >=3.9
License-File: LICENSE
Requires-Dist: jsonschema
Requires-Dist: matplotlib
Requires-Dist: networkx
Requires-Dist: numpy
Requires-Dist: pandas
Requires-Dist: python-dateutil
Requires-Dist: requests
Requires-Dist: scipy
Requires-Dist: pyyaml
Requires-Dist: pandas
Requires-Dist: shortuuid
Requires-Dist: stringcase
Requires-Dist: filelock
Requires-Dist: pathos
Provides-Extra: test
Requires-Dist: pytest; extra == "test"
Requires-Dist: pytest-cov; extra == "test"
Provides-Extra: flowcept
Requires-Dist: flowcept; extra == "flowcept"
Dynamic: license-file
